LICENSE
numpy_ros/__init__.py
numpy_ros/conversions.py
numpy_ros/geometry_msgs.py
numpy_ros-0.1.3.dist-info/LICENSE
numpy_ros-0.1.3.dist-info/WHEEL
numpy_ros-0.1.3.dist-info/METADATA
numpy_ros-0.1.3.dist-info/RECORD
