Metadata-Version: 2.1
Name: numpy-ros
Version: 0.1.3
Summary: Seamlessly convert between ROS messages and NumPy arrays.
Home-page: https://github.com/iamlucaswolf/numpy-ros
License: MIT
Keywords: numpy,ros
Author: Lucas Wolf
Author-email: iamlucaswolf@gmail.com
Requires-Python: >=3.6,<3.10
Classifier: License :: OSI Approved :: MIT License
Classifier: Programming Language :: Python :: 3
Classifier: Programming Language :: Python :: 3.6
Classifier: Programming Language :: Python :: 3.7
Classifier: Programming Language :: Python :: 3.8
Classifier: Programming Language :: Python :: 3.9
Provides-Extra: quaternion-extras
Requires-Dist: numba (>=0.53.1,<0.54.0); extra == "quaternion-extras"
Requires-Dist: numpy (>=1.19.5,<2.0.0)
Requires-Dist: numpy-quaternion (>=2021.4.5,<2022.0.0)
Requires-Dist: scipy (>=0.18.0); extra == "quaternion-extras"
Project-URL: Repository, https://github.com/iamlucaswolf/numpy-ros
